apple_client_secret/__init__.py
apple_client_secret/main.py
apple_client_secret-0.1.2.dist-info/entry_points.txt
apple_client_secret-0.1.2.dist-info/WHEEL
apple_client_secret-0.1.2.dist-info/METADATA
apple_client_secret-0.1.2.dist-info/RECORD
