Metadata-Version: 2.1
Name: apple-client-secret
Version: 0.1.2
Summary: Generate a client_secret for Apple Sign-in
License: Apache2
Author: Your Name
Author-email: you@example.com
Requires-Python: >=3.9,<4.0
Classifier: License :: Other/Proprietary License
Classifier: Programming Language :: Python :: 3
Classifier: Programming Language :: Python :: 3.10
Classifier: Programming Language :: Python :: 3.9
Requires-Dist: PyJWT[crypto] (>=2.3.0,<3.0.0)
Requires-Dist: click (<8.1.0)
Requires-Dist: typer (>=0.4.0,<0.5.0)
